ddd/__init__.py
ddd/domain/__init__.py
ddd/domain/model/__init__.py
ddd/domain/model/aggregate.py
ddd/domain/model/aggregate_root.py
ddd/domain/model/entity.py
ddd/domain/model/value_object.py
ddd/domain/model/exceptions/__init__.py
ddd/domain/model/exceptions/entity_not_found_exception.py
ddd/infrastructure/__init__.py
ddd/infrastructure/repository/__init__.py
ddd/infrastructure/repository/irepository.py
ddd/infrastructure/repository/datastore/__init__.py
ddd/infrastructure/repository/datastore/datastore_repository_base.py
ddd/infrastructure/repository/in_memory/__init__.py
ddd/infrastructure/repository/in_memory/in_memory_repository_base.py
py_domain_driven_design-1.0.0a2.dist-info/LICENSE
py_domain_driven_design-1.0.0a2.dist-info/METADATA
py_domain_driven_design-1.0.0a2.dist-info/WHEEL
py_domain_driven_design-1.0.0a2.dist-info/top_level.txt
py_domain_driven_design-1.0.0a2.dist-info/RECORD
