Metadata-Version: 2.1
Name: py-domain-driven-design
Version: 1.0.0a2
Summary: A domain-driven design library for Python.
Home-page: https://github.com/runemalm/py-domain-driven-design
Author: David Runemalm, 2024
Author-email: david.runemalm@gmail.com
License: GNU General Public License v3.0
Project-URL: Documentation, https://py-domain-driven-design.readthedocs.io/en/latest/
Project-URL: Bug Tracker, https://github.com/runemalm/py-domain-driven-design/issues
Classifier: Development Status :: 3 - Alpha
Classifier: Intended Audience :: Developers
Classifier: License :: OSI Approved :: GNU General Public License v3 (GPLv3)
Classifier: Programming Language :: Python :: 3.7
Classifier: Programming Language :: Python :: 3.8
Classifier: Programming Language :: Python :: 3.9
Classifier: Programming Language :: Python :: 3.10
Classifier: Programming Language :: Python :: 3.11
Classifier: Programming Language :: Python :: 3.12
Classifier: Topic :: Software Development :: Libraries :: Python Modules
Requires-Python: >=3.7
License-File: LICENSE
